__init__.py
not_setup.py
setup2.py
test.py
timsort.so
customtimsort-0.0.117.dist-info/LICENSE
customtimsort-0.0.117.dist-info/METADATA
customtimsort-0.0.117.dist-info/WHEEL
customtimsort-0.0.117.dist-info/top_level.txt
customtimsort-0.0.117.dist-info/RECORD
