Metadata-Version: 2.1
Name: customtimsort
Version: 0.0.117
Summary: Timsort sorting algorithm with custom minrun
Home-page: https://github.com/lehatrutenb/FastTimSort
Author: lehatr
Author-email: lehatrutenb@gmail.com
License: UNKNOWN
Platform: UNKNOWN
Classifier: Programming Language :: Python :: 3
Classifier: License :: OSI Approved :: MIT License
Classifier: Operating System :: OS Independent
Requires-Python: >=2
